pr_install_pack/__init__.py
pr_install_pack/database/__init__.py
pr_install_pack/database/models.py
pr_install_pack/services/__init__.py
pr_install_pack/services/greets.py
pr_install_pack-0.1.0.dist-info/WHEEL
pr_install_pack-0.1.0.dist-info/entry_points.txt
pr_install_pack-0.1.0.dist-info/METADATA
pr_install_pack-0.1.0.dist-info/RECORD
