Metadata-Version: 2.3
Name: pr-install-pack
Version: 0.1.0
Summary: Prueba de instalacion de paquete
Author: jcvillaaa
Author-email: jcvillaaa <juancamilovillaagudelo@gmail.com>
Requires-Dist: httpx>=0.28.1
Requires-Dist: python-dotenv>=1.1.1
Requires-Dist: sqlalchemy>=2.0.43
Requires-Python: >=3.11
